pyproms/__init__.py
pyproms/owlclass.py
pyproms/proms_error.py
pyproms/proms_report.py
pyproms/proms_report_basic.py
pyproms/proms_report_external.py
pyproms/proms_report_internal.py
pyproms/proms_reportingsystem.py
pyproms/prov_activity.py
pyproms/prov_agent.py
pyproms/prov_entity.py
pyproms/report_sender.py
pyproms-1.5.0.dist-info/METADATA
pyproms-1.5.0.dist-info/RECORD
pyproms-1.5.0.dist-info/WHEEL
pyproms-1.5.0.dist-info/top_level.txt
