Metadata-Version: 2.1
Name: pyproms
Version: 1.5.0
Summary: PyPROMS is a client library to make provenance documents and submit them to a PROMS Server instance
Home-page: https://github.com/CSIRO-enviro-informatics/pyproms
Author: Nicholas Car
Author-email: nicholas.car@csiro.au
License: LICENSE.txt
Download-URL: https://github.com/CSIRO-enviro-informatics/pyproms/archive/v1.5.0.tar.gz
Keywords: rdf,prov,prov-o,proms,proms-o,provenance
Platform: UNKNOWN
Classifier: Development Status :: 3 - Alpha
Classifier: Topic :: Utilities
Classifier: License :: OSI Approved :: GNU General Public License v3 or later (GPLv3+)
Classifier: Intended Audience :: Developers
Classifier: License :: OSI Approved :: MIT License
Classifier: Natural Language :: English
Classifier: Programming Language :: Python :: 3
Classifier: Programming Language :: Python :: 3.4
Classifier: Programming Language :: Python :: 3.5
Classifier: Programming Language :: Python :: 3.6
Classifier: Programming Language :: Python :: Implementation :: PyPy
Classifier: Topic :: Software Development :: Libraries :: Python Modules
Requires-Dist: rdflib (>=4.0.0)
Requires-Dist: requests
